sketchify/Gaussian Filtering.py
sketchify/sketch.py
sketchify-0.0.7.dist-info/LICENSE
sketchify-0.0.7.dist-info/METADATA
sketchify-0.0.7.dist-info/WHEEL
sketchify-0.0.7.dist-info/top_level.txt
sketchify-0.0.7.dist-info/RECORD
