Metadata-Version: 2.1
Name: sketchify
Version: 0.0.7
Summary: A simple sketching package which converts images into drawings.
Home-page: https://github.com/grokwithrahul/sketchify
Author: Rahul Prabhu
Author-email: rahul@grokwithrahul.com
License: UNKNOWN
Platform: UNKNOWN
Requires-Dist: opencv-contrib-python
